missing_mechanism/__init__.py
missing_mechanism/core.py
missing_mechanism-0.2.3.dist-info/METADATA
missing_mechanism-0.2.3.dist-info/WHEEL
missing_mechanism-0.2.3.dist-info/top_level.txt
missing_mechanism-0.2.3.dist-info/RECORD
