Metadata-Version: 2.4
Name: missing_mechanism
Version: 0.2.3
Summary: A package for handling missing data intelligently
Author: Rayan Dayyeh
Requires-Python: >=3.6
Requires-Dist: pandas
Dynamic: author
Dynamic: requires-dist
Dynamic: requires-python
Dynamic: summary
